textify4llm/__init__.py
textify4llm/main.py
textify4llm/textify.py
textify4llm-0.2.1.dist-info/METADATA
textify4llm-0.2.1.dist-info/WHEEL
textify4llm-0.2.1.dist-info/licenses/LICENSE
textify4llm-0.2.1.dist-info/RECORD
